designBool.v
module boole(input a,b,c,output y);
wire p1,p2,p3;
assign y=p1+p2+p3;
and(p1,a,b);
and(p2,b,c);
and(p3,a,c);
endmodule

testBool.v
module bool_tb();
reg a,b,c;
wire y;
boole uut(.a(a),.b(b),.c(c),.y(y));
initial begin
$display("A\tB\tC\tY");
$monitor("%b\t%b\t%b\t%b",a,b,c,y);
$dumpfile("bool.vcd");
$dumpvars(1);
a=0;b=0;c=0;#10;
a=0;b=0;c=1;#10;
a=0;b=1;c=0;#10;
a=0;b=1;c=1;#10;
a=1;b=0;c=0;#10;
a=1;b=0;c=1;#10;
a=1;b=1;c=0;#10;
a=1;b=1;c=1;#10;
end;
endmodule

bool.vcd
$date
	Thu Jul 11 16:55:51 2024
$end
$version
	Icarus Verilog
$end
$timescale
	1s
$end
$scope module bool_tb $end
$var wire 1 ! y $end
$var reg 1 " a $end
$var reg 1 # b $end
$var reg 1 $ c $end
$upscope $end
$enddefinitions $end
$comment Show the parameter values. $end
$dumpall
$end
#0
$dumpvars
0$
0#
0"
0!
$end
#10
1$
#20
0$
1#
#30
1!
1$
#40
0!
0$
0#
1"
#50
1!
1$
#60
1!
0$
1#
#70
1!
1$
