designFA.v
module designFA(input a,b,cin,output s,cout);
wire p1,p2,p3;
assign p1=a^b;
assign p3=a&b;
assign s=p1^cin;
assign p2=p1&cin;
assign cout=p3+p2;
endmodule;

testFA.v
module testFA();
reg a,b,cin;
wire s,cout;
designFA uut(.a(a),.b(b),.cin(cin),.s(s),.cout);
initial begin
$display("A\tB\tCin\tSum\tCout");
$monitor("%b\t%b\t%b\t%b\t%b",a,b,cin,s,cout);
$dumpfile("FA.vcd");
$dumpvars(1);
a=0;b=0;cin=0;#10;
a=0;b=0;cin=1;#10;
a=0;b=1;cin=0;#10;
a=0;b=1;cin=1;#10;
a=1;b=0;cin=0;#10;
a=1;b=0;cin=1;#10;
a=1;b=1;cin=0;#10;
a=1;b=1;cin=1;#10;
end;
endmodule

FA.vcd
$date
	Thu Jul 11 17:30:38 2024
$end
$version
	Icarus Verilog
$end
$timescale
	1s
$end
$scope module testFA $end
$var wire 1 ! s $end
$var wire 1 " cout $end
$var reg 1 # a $end
$var reg 1 $ b $end
$var reg 1 % cin $end
$upscope $end
$enddefinitions $end
$comment Show the parameter values. $end
$dumpall
$end
#0
$dumpvars
0%
0$
0#
0"
0!
$end
#10
1!
1%
#20
0%
1$
#30
0!
1"
1%
#40
1!
0"
0%
0$
1#
#50
0!
1"
1%
#60
1"
0%
1$
#70
1!
1%
