designFS.v
module designFS(input a,b,bin,output d,bout);
assign diff1=a^b;
xor(d,diff1,bin);
assign diff2=~a&b;
assign bout=diff2+(~diff1&bin);
endmodule;

testFS.v
module testFS();
reg a,b,bin;
wire d,bout;
designFS fs(a,b,bin,d,bout);
initial begin
$display("A\tB\tBorrow In\tDifference\tBorrow Out");
$monitor("%b\t%b\t%b\t%b\t%b",a,b,bin,d,bout);
$dumpfile("FS.vcd");
$dumpvars(1);
a=0;b=0;bin=0;#10;
a=0;b=0;bin=1;#10;
a=0;b=1;bin=0;#10;
a=0;b=1;bin=1;#10;
a=1;b=0;bin=0;#10;
a=1;b=0;bin=1;#10;
a=1;b=1;bin=0;#10;
a=1;b=1;bin=1;#10;
end;
endmodule

FS.vcd
$date
	Thu Jul 11 20:12:27 2024
$end
$version
	Icarus Verilog
$end
$timescale
	1s
$end
$scope module testFS $end
$var wire 1 ! d $end
$var wire 1 " bout $end
$var reg 1 # a $end
$var reg 1 $ b $end
$var reg 1 % bin $end
$upscope $end
$enddefinitions $end
$comment Show the parameter values. $end
$dumpall
$end
#0
$dumpvars
0%
0$
0#
0"
0!
$end
#10
1!
1"
1%
#20
1"
0%
1$
#30
0!
1%
#40
1!
0"
0%
0$
1#
#50
0!
1%
#60
0%
1$
#70
1!
1"
1%
